{
  "miniprogramRoot": "dist/weapp/",
  "projectname": "taro-mini-app",
  "description": "taro-mini-app",
  "appid": "wx98734f3e90ec1916",
  "setting": {
    "urlCheck": true,
    "es6": true,
    "enhance": true,
    "compileHotReLoad": false,
    "postcss": true,
    "preloadBackgroundData": false,
    "minified": true,
    "newFeature": true,
    "autoAudits": false,
    "coverView": true,
    "showShadowRootInWxmlPanel": false,
    "scopeDataCheck": false,
    "useCompilerModule": false,
    "babelSetting": {
      "ignore": [],
      "disablePlugins": [],
      "outputPath": ""
    },
    "minifyWXSS": true,
    "minifyWXML": true
  },
  "compileType": "miniprogram",
  "simulatorType": "wechat",
  "simulatorPluginLibVersion": {},
  "srcMiniprogramRoot": "dist/weapp/",
  "condition": {},
  "libVersion": "3.7.0",
  "packOptions": {
    "ignore": [],
    "include": []
  },
  "editorSetting": {
    "tabIndent": "insertSpaces",
    "tabSize": 2
  }
}